{
 "total": 161,
 "limit": 161,
 "offset": 0,
 "data": [
  {
   "city": "chicago",
   "name": "Jerri Helms",
   "title": "HarperCollins Christian Publishing",
   "company": "",
   "image": "https://assets.swoogo.com/uploads/medium/4664853-6745f3139bdd8.png",
   "href": "https://www.digitalsummit.com/chicago/speaker/1837999/jerri-helms"
  },
  {
   "city": "chicago",
   "name": "Purna Virji",
   "title": "Agent-Led Growth",
   "company": "",
   "image": "https://assets.swoogo.com/uploads/medium/2926342-650bcf271ec44.jpg",
   "href": "https://www.digitalsummit.com/chicago/speaker/1838000/purna-virji"
  },
  {
   "city": "chicago",
   "name": "Sahirah Johnson",
   "title": "Meta",
   "company": "",
   "image": "https://assets.swoogo.com/uploads/medium/4626734-6732591764eb8.png",
   "href": "https://www.digitalsummit.com/chicago/speaker/1838001/sahirah-johnson"
  },
  {
   "city": "chicago",
   "name": "Jessica Best",
   "title": "BetterAve",
   "company": "",
   "image": "https://assets.swoogo.com/uploads/medium/2926372-650bd3b765a88.jpg",
   "href": "https://www.digitalsummit.com/chicago/speaker/1838010/jessica-best"
  },
  {
   "city": "chicago",
   "name": "Matt Ingwalson",
   "title": "Optimism Delivers",
   "company": "",
   "image": "https://assets.swoogo.com/uploads/medium/5392685-6835f96bb63e1.png",
   "href": "https://www.digitalsummit.com/chicago/speaker/2020694/matt-ingwalson"
  },
  {
   "city": "chicago",
   "name": "Tyler Farnsworth",
   "title": "Campfire",
   "company": "",
   "image": "https://assets.swoogo.com/uploads/medium/6073070-691259186c63f.png",
   "href": "https://www.digitalsummit.com/chicago/speaker/2020695/tyler-farnsworth"
  },
  {
   "city": "chicago",
   "name": "Thea Neal",
   "title": "Kansas City Chiefs",
   "company": "",
   "image": "https://assets.swoogo.com/uploads/medium/3626814-65e0e9fa092d2.jpg",
   "href": "https://www.digitalsummit.com/chicago/speaker/2020698/thea-neal"
  },
  {
   "city": "chicago",
   "name": "Michael Hoffman",
   "title": "Gather Voices",
   "company": "",
   "image": "https://assets.swoogo.com/uploads/medium/3823690-66217430d48e4.png",
   "href": "https://www.digitalsummit.com/chicago/speaker/2020701/michael-hoffman"
  },
  {
   "city": "chicago",
   "name": "Lauren Teague",
   "title": "FANWAGN",
   "company": "",
   "image": "https://assets.swoogo.com/uploads/medium/2926386-650bd57f7c21e.jpg",
   "href": "https://www.digitalsummit.com/chicago/speaker/2020702/lauren-teague"
  },
  {
   "city": "chicago",
   "name": "Ayat Shukairy",
   "title": "Invesp",
   "company": "",
   "image": "https://assets.swoogo.com/uploads/medium/4155902-668bf6ec561fc.png",
   "href": "https://www.digitalsummit.com/chicago/speaker/2020703/ayat-shukairy"
  },
  {
   "city": "chicago",
   "name": "Stephanie Ristow",
   "title": "Ristow Marketing",
   "company": "",
   "image": "https://assets.swoogo.com/uploads/medium/3781610-661816189aa03.png",
   "href": "https://www.digitalsummit.com/chicago/speaker/2020704/stephanie-ristow"
  },
  {
   "city": "chicago",
   "name": "Samantha Kermode",
   "title": "Juristat",
   "company": "",
   "image": "https://assets.swoogo.com/uploads/medium/6717704-69bda2a68900c.png",
   "href": "https://www.digitalsummit.com/chicago/speaker/2032075/samantha-kermode"
  },
  {
   "city": "chicago",
   "name": "Derek Hubbard",
   "title": "Global Brand & Communications Executive Leader",
   "company": "",
   "image": "https://assets.swoogo.com/uploads/medium/6110807-691e2b28bd1d7.png",
   "href": "https://www.digitalsummit.com/chicago/speaker/2034732/derek-hubbard"
  },
  {
   "city": "chicago",
   "name": "Dana Schmidt",
   "title": "Slice Communications",
   "company": "",
   "image": "https://assets.swoogo.com/uploads/medium/5858763-68d2eda3bab80.png",
   "href": "https://www.digitalsummit.com/chicago/speaker/2036416/dana-schmidt"
  },
  {
   "city": "chicago",
   "name": "Kim Stricker",
   "title": "Social Motto",
   "company": "",
   "image": "https://assets.swoogo.com/uploads/medium/6114873-691f492aaab17.png",
   "href": "https://www.digitalsummit.com/chicago/speaker/2036592/kim-stricker"
  },
  {
   "city": "chicago",
   "name": "Susan Wenograd",
   "title": "Warschawski",
   "company": "",
   "image": "https://assets.swoogo.com/uploads/medium/6779833-69cd79c791971.png",
   "href": "https://www.digitalsummit.com/chicago/speaker/2036711/susan-wenograd"
  },
  {
   "city": "chicago",
   "name": "Tyler Lane",
   "title": "Session Interactive",
   "company": "",
   "image": "https://assets.swoogo.com/uploads/medium/5415071-683e5a1fa849c.png",
   "href": "https://www.digitalsummit.com/chicago/speaker/2036717/tyler-lane"
  },
  {
   "city": "chicago",
   "name": "Liam Wade",
   "title": "Impression",
   "company": "",
   "image": "https://assets.swoogo.com/uploads/medium/6358224-697ad94ebabe2.png",
   "href": "https://www.digitalsummit.com/chicago/speaker/2127126/liam-wade"
  },
  {
   "city": "chicago",
   "name": "Steve Krull",
   "title": "Be Found Online (BFO)",
   "company": "",
   "image": "https://assets.swoogo.com/uploads/medium/3745890-660dbcb12346f.jpg",
   "href": "https://www.digitalsummit.com/chicago/speaker/2131870/steve-krull"
  },
  {
   "city": "chicago",
   "name": "John Johnson",
   "title": "Vibes",
   "company": "",
   "image": "https://assets.swoogo.com/uploads/medium/6372289-697d1c37a3e0e.png",
   "href": "https://www.digitalsummit.com/chicago/speaker/2131916/john-johnson"
  },
  {
   "city": "chicago",
   "name": "John Triplett",
   "title": "IDX",
   "company": "",
   "image": "https://assets.swoogo.com/uploads/medium/6105647-691ce52ed104f.png",
   "href": "https://www.digitalsummit.com/chicago/speaker/2134133/john-triplett"
  },
  {
   "city": "chicago",
   "name": "David Shing",
   "title": "Shingy",
   "company": "",
   "image": "https://assets.swoogo.com/uploads/medium/2950650-65145fd394eea.jpg",
   "href": "https://www.digitalsummit.com/chicago/speaker/2167721/david-shing"
  },
  {
   "city": "chicago",
   "name": "Julia Fedor",
   "title": "United Airlines",
   "company": "",
   "image": "https://assets.swoogo.com/uploads/medium/5024981-67c7882ca16e5.png",
   "href": "https://www.digitalsummit.com/chicago/speaker/2191477/julia-fedor"
  },
  {
   "city": "chicago",
   "name": "Paul Holte",
   "title": "United Airlines",
   "company": "",
   "image": "https://assets.swoogo.com/uploads/medium/6020733-68ffdb1a7838a.png",
   "href": "https://www.digitalsummit.com/chicago/speaker/2191478/paul-holte"
  },
  {
   "city": "chicago",
   "name": "Jenny Haggard",
   "title": "Spotify",
   "company": "",
   "image": "https://assets.swoogo.com/uploads/medium/2958164-651588f72a01d.jpg",
   "href": "https://www.digitalsummit.com/chicago/speaker/2198980/jenny-haggard"
  },
  {
   "city": "chicago",
   "name": "Nate Tower",
   "title": "Perrill Digital Marketing",
   "company": "",
   "image": "https://assets.swoogo.com/uploads/medium/3918573-663e7b73ee3e5.png",
   "href": "https://www.digitalsummit.com/chicago/speaker/2234845/nate-tower"
  },
  {
   "city": "chicago",
   "name": "Ariana Keil",
   "title": "Canto",
   "company": "",
   "image": "https://assets.swoogo.com/uploads/medium/4454346-66f32dbf89718.png",
   "href": "https://www.digitalsummit.com/chicago/speaker/2234856/ariana-keil"
  },
  {
   "city": "chicago",
   "name": "Michael Heller",
   "title": "IDX",
   "company": "",
   "image": "https://assets.swoogo.com/uploads/medium/6787269-69cecf31c9b1b.png",
   "href": "https://www.digitalsummit.com/chicago/speaker/2234861/michael-heller"
  },
  {
   "city": "chicago",
   "name": "Nikole Hollis",
   "title": "Your Community App",
   "company": "",
   "image": "https://assets.swoogo.com/uploads/medium/6770473-69cc0ca6e501c.jpeg",
   "href": "https://www.digitalsummit.com/chicago/speaker/2257834/nikole-hollis"
  },
  {
   "city": "chicago",
   "name": "Alli Pyle",
   "title": "Retronyms",
   "company": "",
   "image": "https://assets.swoogo.com/uploads/medium/6770498-69cc0d7994fcb.jpg",
   "href": "https://www.digitalsummit.com/chicago/speaker/2257837/alli-pyle"
  },
  {
   "city": "chicago",
   "name": "Dustin Diehl",
   "title": "IDX",
   "company": "",
   "image": "https://assets.swoogo.com/uploads/medium/6779325-69cd6eadefe9c.png",
   "href": "https://www.digitalsummit.com/chicago/speaker/2261318/dustin-diehl"
  },
  {
   "city": "chicago",
   "name": "Dana Crow",
   "title": "IDX",
   "company": "",
   "image": "https://assets.swoogo.com/uploads/medium/6787280-69cecfcf85352.png",
   "href": "https://www.digitalsummit.com/chicago/speaker/2263696/dana-crow"
  },
  {
   "city": "chicago",
   "name": "Cherie Dupor",
   "title": "Senior Lifestyle",
   "company": "",
   "image": "https://assets.swoogo.com/uploads/medium/6787295-69ced07469e06.png",
   "href": "https://www.digitalsummit.com/chicago/speaker/2263697/cherie-dupor"
  },
  {
   "city": "chicago",
   "name": "Krystyna Keena",
   "title": "Senior Lifestyle",
   "company": "",
   "image": "https://assets.swoogo.com/uploads/medium/6787315-69ced1418a863.png",
   "href": "https://www.digitalsummit.com/chicago/speaker/2263699/krystyna-keena"
  },
  {
   "city": "chicago",
   "name": "Monica Cravotta",
   "title": "Bluehost",
   "company": "",
   "image": "https://assets.swoogo.com/uploads/medium/6791883-69d015609bf92.png",
   "href": "https://www.digitalsummit.com/chicago/speaker/2264864/monica-cravotta"
  },
  {
   "city": "chicago",
   "name": "Kyle Geib",
   "title": "Be Found Online",
   "company": "",
   "image": "https://assets.swoogo.com/uploads/medium/6812540-69d652b4ec9ca.png",
   "href": "https://www.digitalsummit.com/chicago/speaker/2268570/kyle-geib"
  },
  {
   "city": "chicago",
   "name": "Sean Sweeney",
   "title": "First Position Digital Solutions",
   "company": "",
   "image": "https://assets.swoogo.com/uploads/medium/5013656-67c5efc4bd30d.png",
   "href": "https://www.digitalsummit.com/chicago/speaker/2268576/sean-sweeney"
  },
  {
   "city": "denver",
   "name": "Emma Kuhl Pitts",
   "title": "PullSpark",
   "company": "",
   "image": "https://assets.swoogo.com/uploads/medium/6301722-696faa5196b51.png",
   "href": "https://www.digitalsummit.com/denver/speaker/2099542/emma-kuhl-pitts"
  },
  {
   "city": "denver",
   "name": "Sarah Foley",
   "title": "University of Denver",
   "company": "",
   "image": "https://assets.swoogo.com/uploads/medium/6336772-69778a9129200.png",
   "href": "https://www.digitalsummit.com/denver/speaker/2116966/sarah-foley"
  },
  {
   "city": "denver",
   "name": "Angela Clark",
   "title": "Patagonia",
   "company": "",
   "image": "https://assets.swoogo.com/uploads/medium/5079074-67d8b3441ed2d.png",
   "href": "https://www.digitalsummit.com/denver/speaker/2117341/angela-clark"
  },
  {
   "city": "denver",
   "name": "Greg Gifford",
   "title": "SearchLab",
   "company": "",
   "image": "https://assets.swoogo.com/uploads/medium/6373227-697d3ddb583f4.png",
   "href": "https://www.digitalsummit.com/denver/speaker/2117520/greg-gifford"
  },
  {
   "city": "denver",
   "name": "Meredith Howard",
   "title": "Best Practice Media",
   "company": "",
   "image": "https://assets.swoogo.com/uploads/medium/3557839-65cd03cb7a306.png",
   "href": "https://www.digitalsummit.com/denver/speaker/2118257/meredith-howard"
  },
  {
   "city": "denver",
   "name": "Wil Reynolds",
   "title": "Seer Interactive",
   "company": "",
   "image": "https://assets.swoogo.com/uploads/medium/5774768-68c354f0708be.png",
   "href": "https://www.digitalsummit.com/denver/speaker/2118259/wil-reynolds"
  },
  {
   "city": "denver",
   "name": "Frank Gregory",
   "title": "Nestle",
   "company": "",
   "image": "https://assets.swoogo.com/uploads/medium/6781082-69cd9df426359.png",
   "href": "https://www.digitalsummit.com/denver/speaker/2118269/frank-gregory"
  },
  {
   "city": "denver",
   "name": "Tobe Awosanya",
   "title": "Data Techcon",
   "company": "",
   "image": "https://assets.swoogo.com/uploads/medium/3749405-660eceb0c2d63.jpg",
   "href": "https://www.digitalsummit.com/denver/speaker/2118270/tobe-awosanya"
  },
  {
   "city": "denver",
   "name": "Shannon Gregg",
   "title": "Cloud Adoption Solutions",
   "company": "",
   "image": "https://assets.swoogo.com/uploads/medium/4091814-6671ab981e9d6.png",
   "href": "https://www.digitalsummit.com/denver/speaker/2118272/shannon-gregg"
  },
  {
   "city": "denver",
   "name": "Niki Mosier",
   "title": "National Academy of Sports Medicine (NASM)",
   "company": "",
   "image": "https://assets.swoogo.com/uploads/medium/3615318-65de022a90e6c.png",
   "href": "https://www.digitalsummit.com/denver/speaker/2131808/niki-mosier"
  },
  {
   "city": "denver",
   "name": "Ashley Nelson",
   "title": "Estee Lauder/ Smashbox",
   "company": "",
   "image": "https://assets.swoogo.com/uploads/medium/3667596-65f0783725a41.jpg",
   "href": "https://www.digitalsummit.com/denver/speaker/2131813/ashley-nelson"
  },
  {
   "city": "denver",
   "name": "Christina Milanowski",
   "title": "Curious Plot",
   "company": "",
   "image": "https://assets.swoogo.com/uploads/medium/6373202-697d3caf9547c.png",
   "href": "https://www.digitalsummit.com/denver/speaker/2132020/christina-milanowski"
  },
  {
   "city": "denver",
   "name": "Shari Spooner",
   "title": "Curious Plot",
   "company": "",
   "image": "https://assets.swoogo.com/uploads/medium/6373245-697d3e83d092f.png",
   "href": "https://www.digitalsummit.com/denver/speaker/2132021/shari-spooner"
  },
  {
   "city": "denver",
   "name": "John Triplett",
   "title": "IDX",
   "company": "",
   "image": "https://assets.swoogo.com/uploads/medium/6105647-691ce52ed104f.png",
   "href": "https://www.digitalsummit.com/denver/speaker/2134182/john-triplett"
  },
  {
   "city": "denver",
   "name": "John Johnson",
   "title": "Vibes",
   "company": "",
   "image": "https://assets.swoogo.com/uploads/medium/6372289-697d1c37a3e0e.png",
   "href": "https://www.digitalsummit.com/denver/speaker/2134183/john-johnson"
  },
  {
   "city": "denver",
   "name": "Alex Lieberman",
   "title": "Morning Brew",
   "company": "",
   "image": "https://assets.swoogo.com/uploads/medium/5477877-6855688b727a4.png",
   "href": "https://www.digitalsummit.com/denver/speaker/2134902/alex-lieberman"
  },
  {
   "city": "denver",
   "name": "Paige McCrensky",
   "title": "ResonateLab",
   "company": "",
   "image": "https://assets.swoogo.com/uploads/medium/6917025-69ea629d90da1.png",
   "href": "https://www.digitalsummit.com/denver/speaker/2296930/paige-mccrensky"
  },
  {
   "city": "denver",
   "name": "Dustin Diehl",
   "title": "IDX",
   "company": "",
   "image": "https://assets.swoogo.com/uploads/medium/6779325-69cd6eadefe9c.png",
   "href": "https://www.digitalsummit.com/denver/speaker/2308105/dustin-diehl"
  },
  {
   "city": "denver",
   "name": "Patty Radford Henderson",
   "title": "Annum",
   "company": "",
   "image": "https://assets.swoogo.com/uploads/medium/2936781-651158f6dceac.jpg",
   "href": "https://www.digitalsummit.com/denver/speaker/2313726/patty-radford-henderson"
  },
  {
   "city": "denver",
   "name": "Ariana Keil",
   "title": "Canto",
   "company": "",
   "image": "https://assets.swoogo.com/uploads/medium/4454346-66f32dbf89718.png",
   "href": "https://www.digitalsummit.com/denver/speaker/2316396/ariana-keil"
  },
  {
   "city": "denver",
   "name": "Grant Simmons",
   "title": "Waikay",
   "company": "",
   "image": "https://assets.swoogo.com/uploads/medium/2958375-65158cf654f4b.png",
   "href": "https://www.digitalsummit.com/denver/speaker/2316486/grant-simmons"
  },
  {
   "city": "denver",
   "name": "Sharon Harris",
   "title": "The SH Collective",
   "company": "",
   "image": "https://assets.swoogo.com/uploads/medium/4485349-66fc538c07a02.png",
   "href": "https://www.digitalsummit.com/denver/speaker/2316846/sharon-harris"
  },
  {
   "city": "denver",
   "name": "Zach Chahalis",
   "title": "iPullRank",
   "company": "",
   "image": "https://assets.swoogo.com/uploads/medium/5013946-67c5fbd0cac1f.png",
   "href": "https://www.digitalsummit.com/denver/speaker/2324277/zach-chahalis"
  },
  {
   "city": "denver",
   "name": "Monica Cravotta",
   "title": "Bluehost",
   "company": "",
   "image": "https://assets.swoogo.com/uploads/medium/6791883-69d015609bf92.png",
   "href": "https://www.digitalsummit.com/denver/speaker/2336170/monica-cravotta"
  },
  {
   "city": "denver",
   "name": "Quinn Tempest",
   "title": "Create Your Purpose LLC ·",
   "company": "",
   "image": "https://assets.swoogo.com/uploads/medium/7080435-6a18bf2871651.png",
   "href": "https://www.digitalsummit.com/denver/speaker/2338371/quinn-tempest"
  },
  {
   "city": "denver",
   "name": "Barrett Langendoerfer",
   "title": "V Digital Services",
   "company": "",
   "image": "https://assets.swoogo.com/uploads/medium/7093003-6a1dfb13e3206.png",
   "href": "https://www.digitalsummit.com/denver/speaker/2345421/barrett-langendoerfer"
  },
  {
   "city": "denver",
   "name": "Karen Talavera",
   "title": "Synchronicity Marketing™",
   "company": "",
   "image": "https://assets.swoogo.com/uploads/medium/7097665-6a1f2e6f2d3fa.png",
   "href": "https://www.digitalsummit.com/denver/speaker/2352845/karen-talavera"
  },
  {
   "city": "denver",
   "name": "Roger Williams",
   "title": "Kinsta",
   "company": "",
   "image": "https://assets.swoogo.com/uploads/medium/6008747-68fa9ec17ffee.png",
   "href": "https://www.digitalsummit.com/denver/speaker/2354817/roger-williams"
  },
  {
   "city": "denver",
   "name": "Matt Basil",
   "title": "Contentful",
   "company": "",
   "image": "https://assets.swoogo.com/uploads/medium/7110287-6a21c93140225.png",
   "href": "https://www.digitalsummit.com/denver/speaker/2355785/matt-basil"
  },
  {
   "city": "denver",
   "name": "Brian Lasonde",
   "title": "PPC Boost",
   "company": "",
   "image": "https://assets.swoogo.com/uploads/medium/7138713-6a2b2a5750d1b.png",
   "href": "https://www.digitalsummit.com/denver/speaker/2366604/brian-lasonde"
  },
  {
   "city": "denver",
   "name": "Mindy Weinstein",
   "title": "Market MindShift",
   "company": "",
   "image": "https://assets.swoogo.com/uploads/medium/5596013-68894890bf1a1.png",
   "href": "https://www.digitalsummit.com/denver/speaker/2367699/mindy-weinstein"
  },
  {
   "city": "denver",
   "name": "Jared Kleinstein",
   "title": "Gondola / Fresh Tape Media",
   "company": "",
   "image": "https://assets.swoogo.com/uploads/medium/7143961-6a2c7af458a2f.png",
   "href": "https://www.digitalsummit.com/denver/speaker/2368063/jared-kleinstein"
  },
  {
   "city": "denver",
   "name": "Tyler Lane",
   "title": "Session Interactive",
   "company": "",
   "image": "https://assets.swoogo.com/uploads/medium/5415071-683e5a1fa849c.png",
   "href": "https://www.digitalsummit.com/denver/speaker/2368087/tyler-lane"
  },
  {
   "city": "denver",
   "name": "Danielle Blanchette",
   "title": "Digital Summit",
   "company": "",
   "image": "https://assets.swoogo.com/uploads/medium/5612655-689161e688a94.png",
   "href": "https://www.digitalsummit.com/denver/speaker/2368088/danielle-blanchette"
  },
  {
   "city": "raleigh",
   "name": "Susan Wenograd",
   "title": "VP of Digital",
   "company": "Warschawski",
   "image": "https://assets.swoogo.com/uploads/medium/6779833-69cd79c791971.png",
   "href": "https://www.digitalsummit.com/raleigh/speaker/2377416/susan-wenograd"
  },
  {
   "city": "raleigh",
   "name": "Janet Driscoll Miller",
   "title": "President & CEO",
   "company": "Marketing Mojo",
   "image": "https://assets.swoogo.com/uploads/medium/2926367-650bd30ec4532.jpg",
   "href": "https://www.digitalsummit.com/raleigh/speaker/2377417/janet-driscoll-miller"
  },
  {
   "city": "raleigh",
   "name": "Cherise Bernard",
   "title": "Founder and CEO",
   "company": "Modern Work Consultancy",
   "image": "https://assets.swoogo.com/uploads/medium/7186549-6a3c353f9403e.png",
   "href": "https://www.digitalsummit.com/raleigh/speaker/2377419/cherise-bernard"
  },
  {
   "city": "raleigh",
   "name": "Anna McHugh",
   "title": "Senior Principal Information Architect and Taxonomist",
   "company": "Red Hat",
   "image": "https://assets.swoogo.com/uploads/medium/6025833-69011e62b4f70.png",
   "href": "https://www.digitalsummit.com/raleigh/speaker/2377451/anna-mchugh"
  },
  {
   "city": "raleigh",
   "name": "Veronica Romney",
   "title": "Fractional CMO",
   "company": "VeronicaRomney.com",
   "image": "https://assets.swoogo.com/uploads/medium/3613142-65dd08638b155.jpg",
   "href": "https://www.digitalsummit.com/raleigh/speaker/2377455/veronica-romney"
  },
  {
   "city": "raleigh",
   "name": "Dane Saville",
   "title": "Head of Search and AI Visibility",
   "company": "SearchLab",
   "image": "https://assets.swoogo.com/uploads/medium/7171128-6a358a5a6459f.png",
   "href": "https://www.digitalsummit.com/raleigh/speaker/2377483/dane-saville"
  },
  {
   "city": "raleigh",
   "name": "Kipp Bodnar",
   "title": "CMO",
   "company": "HubSpot",
   "image": "https://assets.swoogo.com/uploads/medium/7191321-6a3d680ab5271.png",
   "href": "https://www.digitalsummit.com/raleigh/speaker/2377525/kipp-bodnar"
  },
  {
   "city": "raleigh",
   "name": "Bob Tripathi",
   "title": "Founder",
   "company": "TheVibeMarketing.ai",
   "image": "https://assets.swoogo.com/uploads/medium/2963813-6515dadf74915.jpg",
   "href": "https://www.digitalsummit.com/raleigh/speaker/2377526/bob-tripathi"
  },
  {
   "city": "raleigh",
   "name": "Michael Burke",
   "title": "Managing Director, Commerce",
   "company": "Google",
   "image": "https://assets.swoogo.com/uploads/medium/4735066-6769ea7391bbb.png",
   "href": "https://www.digitalsummit.com/raleigh/speaker/2377527/michael-burke"
  },
  {
   "city": "raleigh",
   "name": "Michael King",
   "title": "CEO | Executive Coach",
   "company": "Teams.Coach",
   "image": "https://assets.swoogo.com/uploads/medium/7171536-6a35ae398bdd9.png",
   "href": "https://www.digitalsummit.com/raleigh/speaker/2377539/michael-king"
  },
  {
   "city": "raleigh",
   "name": "Janessa Drainville",
   "title": "Senior Demand Generation Content Strategist, Central AI",
   "company": "Atlassian",
   "image": "https://assets.swoogo.com/uploads/medium/7171721-6a35cce2ba7ae.png",
   "href": "https://www.digitalsummit.com/raleigh/speaker/2377568/janessa-drainville"
  },
  {
   "city": "raleigh",
   "name": "Andy Waldrop",
   "title": "VP Digital Experiences & AI Innovation",
   "company": "WebMD",
   "image": "https://assets.swoogo.com/uploads/medium/7190295-6a3d49c2a1576.png",
   "href": "https://www.digitalsummit.com/raleigh/speaker/2378923/andy-waldrop"
  },
  {
   "city": "raleigh",
   "name": "Paxton Gray",
   "title": "CEO",
   "company": "97th Floor",
   "image": "https://assets.swoogo.com/uploads/medium/3749575-660ecfe101e97.jpg",
   "href": "https://www.digitalsummit.com/raleigh/speaker/2380666/paxton-gray"
  },
  {
   "city": "raleigh",
   "name": "Hilary Sutton",
   "title": "Founder",
   "company": "HSL Digital",
   "image": "https://assets.swoogo.com/uploads/medium/3775132-6616cb8a07625.png",
   "href": "https://www.digitalsummit.com/raleigh/speaker/2385702/hilary-sutton"
  },
  {
   "city": "raleigh",
   "name": "Matt Sutor",
   "title": "Chief Marketing Officer",
   "company": "Carolina Hurricanes",
   "image": "https://assets.swoogo.com/uploads/medium/5749385-68befc8511809.png",
   "href": "https://www.digitalsummit.com/raleigh/speaker/2386298/matt-sutor"
  },
  {
   "city": "raleigh",
   "name": "Cassaundra Bernat",
   "title": "Sr. Digital Manager",
   "company": "Bojangles'​ Restaurants, Inc.",
   "image": "https://assets.swoogo.com/uploads/medium/7218112-6a466f1a8722e.png",
   "href": "https://www.digitalsummit.com/raleigh/speaker/2392545/cassaundra-bernat"
  },
  {
   "city": "dallas",
   "name": "Derek Hubbard",
   "title": "Global Brand & Communications Executive Leader",
   "company": "",
   "image": "https://assets.swoogo.com/uploads/medium/6110807-691e2b28bd1d7.png",
   "href": "https://www.digitalsummit.com/dallas/speaker/2413501/derek-hubbard"
  },
  {
   "city": "dallas",
   "name": "Colleen Harris",
   "title": "Director of Product Insights",
   "company": "DealerOn",
   "image": "https://assets.swoogo.com/uploads/medium/2958670-6515938207bc8.jpg",
   "href": "https://www.digitalsummit.com/dallas/speaker/2413517/colleen-harris"
  },
  {
   "city": "dallas",
   "name": "Rob Sender",
   "title": "Senior Director, Brand & Marketing",
   "company": "Dallas Cowboys",
   "image": "https://assets.swoogo.com/uploads/medium/7273209-6a590cd424f45.png",
   "href": "https://www.digitalsummit.com/dallas/speaker/2413777/rob-sender"
  },
  {
   "city": "dallas",
   "name": "A. Lee Judge",
   "title": "Co-Founder and CMO",
   "company": "Content Monsta",
   "image": "https://assets.swoogo.com/uploads/medium/3626420-65e0db3568ae9.jpg",
   "href": "https://www.digitalsummit.com/dallas/speaker/2415253/a.-lee-judge"
  },
  {
   "city": "dallas",
   "name": "Wil Reynolds",
   "title": "VP Innovation",
   "company": "Seer Interactive",
   "image": "https://assets.swoogo.com/uploads/medium/5774768-68c354f0708be.png",
   "href": "https://www.digitalsummit.com/dallas/speaker/2415254/wil-reynolds"
  },
  {
   "city": "dallas",
   "name": "Jerri Helms",
   "title": "SVP, Marketing Operations",
   "company": "HarperCollins Christian Publishing",
   "image": "https://assets.swoogo.com/uploads/medium/4664853-6745f3139bdd8.png",
   "href": "https://www.digitalsummit.com/dallas/speaker/2415255/jerri-helms"
  },
  {
   "city": "dallas",
   "name": "Sheena Hakimian",
   "title": "Senior Director, Digital Consumer Marketing",
   "company": "Condé Nast",
   "image": "https://assets.swoogo.com/uploads/medium/2945006-65132c1da1af1.jpg",
   "href": "https://www.digitalsummit.com/dallas/speaker/2415256/sheena-hakimian"
  },
  {
   "city": "dallas",
   "name": "Sarah Weise",
   "title": "CEO",
   "company": "Bixa",
   "image": "https://assets.swoogo.com/uploads/medium/3773310-6616841143588.png",
   "href": "https://www.digitalsummit.com/dallas/speaker/2415257/sarah-weise"
  },
  {
   "city": "dallas",
   "name": "Lauren Teague",
   "title": "Founder",
   "company": "FANWAGN",
   "image": "https://assets.swoogo.com/uploads/medium/2926386-650bd57f7c21e.jpg",
   "href": "https://www.digitalsummit.com/dallas/speaker/2415258/lauren-teague"
  },
  {
   "city": "dallas",
   "name": "Ginger Shimp",
   "title": "Global Content Lead and Senior Marketing Director",
   "company": "SAP",
   "image": "https://assets.swoogo.com/uploads/medium/5563867-687a3de018d1e.png",
   "href": "https://www.digitalsummit.com/dallas/speaker/2415260/ginger-shimp"
  },
  {
   "city": "dallas",
   "name": "Jon Chang",
   "title": "VP, Growth Marketing",
   "company": "MyFitnessPal",
   "image": "https://assets.swoogo.com/uploads/medium/3290881-65676cf52c2b1.jpg",
   "href": "https://www.digitalsummit.com/dallas/speaker/2418792/jon-chang"
  },
  {
   "city": "minneapolis",
   "name": "Rand Fishkin",
   "title": "CEO & Co-Founder",
   "company": "SparkToro",
   "image": "https://assets.swoogo.com/uploads/medium/6752914-69c6c2d198553.png",
   "href": "https://www.digitalsummit.com/minneapolis/speaker/2232839/rand-fishkin"
  },
  {
   "city": "minneapolis",
   "name": "Andy Crestodina",
   "title": "Co-Founder and CMO",
   "company": "Orbit Media Studios",
   "image": "https://assets.swoogo.com/uploads/medium/4823608-6792c23dc727d.png",
   "href": "https://www.digitalsummit.com/minneapolis/speaker/2232842/andy-crestodina"
  },
  {
   "city": "minneapolis",
   "name": "Nicole Ramirez",
   "title": "Owner",
   "company": "NR Digital Consulting",
   "image": "https://assets.swoogo.com/uploads/medium/6792169-69d01e802a9fa.png",
   "href": "https://www.digitalsummit.com/minneapolis/speaker/2232844/nicole-ramirez"
  },
  {
   "city": "minneapolis",
   "name": "Ryan Pena",
   "title": "Senior Marketing Leader",
   "company": "NMDP",
   "image": "https://assets.swoogo.com/uploads/medium/5513352-686540a6120b4.png",
   "href": "https://www.digitalsummit.com/minneapolis/speaker/2232845/ryan-pena"
  },
  {
   "city": "minneapolis",
   "name": "Jennifer Watson",
   "title": "Social Media Manager",
   "company": "athenahealth",
   "image": "https://assets.swoogo.com/uploads/medium/3773335-66168711baf26.png",
   "href": "https://www.digitalsummit.com/minneapolis/speaker/2232846/jennifer-watson"
  },
  {
   "city": "minneapolis",
   "name": "Joie Healy",
   "title": "Director Global Social Media & Digital Content",
   "company": "Cisco",
   "image": "https://assets.swoogo.com/uploads/medium/3387330-658486d5ee664.jpg",
   "href": "https://www.digitalsummit.com/minneapolis/speaker/2232848/joie-healy"
  },
  {
   "city": "minneapolis",
   "name": "Emma Kuhl Pitts",
   "title": "CEO",
   "company": "PullSpark",
   "image": "https://assets.swoogo.com/uploads/medium/6301722-696faa5196b51.png",
   "href": "https://www.digitalsummit.com/minneapolis/speaker/2232850/emma-kuhl-pitts"
  },
  {
   "city": "minneapolis",
   "name": "Erin Gulden",
   "title": "VP, Client Strategy",
   "company": "The Agency at MSP",
   "image": "https://assets.swoogo.com/uploads/medium/5124928-67e445792d30e.png",
   "href": "https://www.digitalsummit.com/minneapolis/speaker/2232852/erin-gulden"
  },
  {
   "city": "minneapolis",
   "name": "Ashley Zeckman",
   "title": "VP, Influencer Relations",
   "company": "Spotlight",
   "image": "https://assets.swoogo.com/uploads/medium/5289094-68128ab03757f.png",
   "href": "https://www.digitalsummit.com/minneapolis/speaker/2232853/ashley-zeckman"
  },
  {
   "city": "minneapolis",
   "name": "Annie Scott",
   "title": "Marketing Leader",
   "company": "",
   "image": "https://assets.swoogo.com/uploads/medium/6715313-69bd559478c60.png",
   "href": "https://www.digitalsummit.com/minneapolis/speaker/2236115/annie-scott"
  },
  {
   "city": "minneapolis",
   "name": "Matt DeWolf",
   "title": "Founder",
   "company": "MK Quinn Media",
   "image": "https://assets.swoogo.com/uploads/medium/6716488-69bd799b2eb5f.png",
   "href": "https://www.digitalsummit.com/minneapolis/speaker/2236585/matt-dewolf"
  },
  {
   "city": "minneapolis",
   "name": "Dave Meyer",
   "title": "President",
   "company": "BizzyWeb",
   "image": "https://assets.swoogo.com/uploads/medium/6732640-69c2d7010ebec.png",
   "href": "https://www.digitalsummit.com/minneapolis/speaker/2242943/dave-meyer"
  },
  {
   "city": "minneapolis",
   "name": "Arik Hanson",
   "title": "Principal",
   "company": "Arik Hanson Social Media",
   "image": "https://assets.swoogo.com/uploads/medium/6744893-69c54c814696e.png",
   "href": "https://www.digitalsummit.com/minneapolis/speaker/2248511/arik-hanson"
  },
  {
   "city": "minneapolis",
   "name": "Craig Pladson",
   "title": "Founder",
   "company": "Brave Co.",
   "image": "https://assets.swoogo.com/uploads/medium/6747003-69c5815316f85.png",
   "href": "https://www.digitalsummit.com/minneapolis/speaker/2249453/craig-pladson"
  },
  {
   "city": "minneapolis",
   "name": "John Triplett",
   "title": "Business Development Director",
   "company": "IDX",
   "image": "https://assets.swoogo.com/uploads/medium/6105647-691ce52ed104f.png",
   "href": "https://www.digitalsummit.com/minneapolis/speaker/2251257/john-triplett"
  },
  {
   "city": "minneapolis",
   "name": "Greta Brooks",
   "title": "Vice President of Marketing, Communications and Member Services",
   "company": "Wright-Hennepin Cooperative Electric Association",
   "image": "https://assets.swoogo.com/uploads/medium/6771993-69cc3164584eb.png",
   "href": "https://www.digitalsummit.com/minneapolis/speaker/2258963/greta-brooks"
  },
  {
   "city": "minneapolis",
   "name": "Greg Swan",
   "title": "Senior Partner, Head of Futures & Client Transformation",
   "company": "FINN Partners",
   "image": "https://assets.swoogo.com/uploads/medium/7027665-6a0779362d5f0.png",
   "href": "https://www.digitalsummit.com/minneapolis/speaker/2324386/greg-swan"
  },
  {
   "city": "minneapolis",
   "name": "Sharon Harris",
   "title": "CMO",
   "company": "The SH Collective",
   "image": "https://assets.swoogo.com/uploads/medium/4485349-66fc538c07a02.png",
   "href": "https://www.digitalsummit.com/minneapolis/speaker/2335844/sharon-harris"
  },
  {
   "city": "minneapolis",
   "name": "Patty Radford Henderson",
   "title": "Founder & CEO",
   "company": "Annum",
   "image": "https://assets.swoogo.com/uploads/medium/2936781-651158f6dceac.jpg",
   "href": "https://www.digitalsummit.com/minneapolis/speaker/2376178/patty-radford-henderson"
  },
  {
   "city": "minneapolis",
   "name": "Matt Ingwalson",
   "title": "Founder",
   "company": "Optimism Delivers",
   "image": "https://assets.swoogo.com/uploads/medium/5392685-6835f96bb63e1.png",
   "href": "https://www.digitalsummit.com/minneapolis/speaker/2383722/matt-ingwalson"
  },
  {
   "city": "minneapolis",
   "name": "Ryan Huschka",
   "title": "Vice President, Digital Sales",
   "company": "Adtaxi",
   "image": "https://assets.swoogo.com/uploads/medium/7192932-6a3da911b67bb.png",
   "href": "https://www.digitalsummit.com/minneapolis/speaker/2385253/ryan-huschka"
  },
  {
   "city": "minneapolis",
   "name": "David Shing",
   "title": "Digital Prophet",
   "company": "Shingy",
   "image": "https://assets.swoogo.com/uploads/medium/2950650-65145fd394eea.jpg",
   "href": "https://www.digitalsummit.com/minneapolis/speaker/2414926/david-shing"
  },
  {
   "city": "minneapolis",
   "name": "Cari O'Brien",
   "title": "Founder",
   "company": "Ripples Reach Coaching",
   "image": "https://assets.swoogo.com/uploads/medium/6066461-690e566417972.png",
   "href": "https://www.digitalsummit.com/minneapolis/speaker/2417807/cari-o'brien"
  },
  {
   "city": "minneapolis",
   "name": "Erik Bohnhoff",
   "title": "Director of Client Services",
   "company": "Foundry North and the Minnesota Star Tribune",
   "image": "https://assets.swoogo.com/uploads/medium/7286865-6a5e59fd120e1.png",
   "href": "https://www.digitalsummit.com/minneapolis/speaker/2418131/erik-bohnhoff"
  },
  {
   "city": "minneapolis",
   "name": "Liz Andert",
   "title": "Director, Corporate Digital Marketing and Website Operations",
   "company": "H.B. Fuller",
   "image": "https://assets.swoogo.com/uploads/medium/6753771-69c6d61cce9cd.png",
   "href": "https://www.digitalsummit.com/minneapolis/speaker/2420655/liz-andert"
  },
  {
   "city": "philadelphia",
   "name": "Sheena Hakimian",
   "title": "Senior Director, Digital Consumer Marketing",
   "company": "Condé Nast",
   "image": "https://assets.swoogo.com/uploads/medium/2945006-65132c1da1af1.jpg",
   "href": "https://www.digitalsummit.com/philadelphia/speaker/2291635/sheena-hakimian"
  },
  {
   "city": "philadelphia",
   "name": "Tom Shapiro",
   "title": "CEO",
   "company": "Stratabeat, Inc.",
   "image": "https://assets.swoogo.com/uploads/medium/2963116-6515cc66da8fa.jpg",
   "href": "https://www.digitalsummit.com/philadelphia/speaker/2291636/tom-shapiro"
  },
  {
   "city": "philadelphia",
   "name": "Dale Bertrand",
   "title": "Founder & CEO",
   "company": "Fire&Spark",
   "image": "https://assets.swoogo.com/uploads/medium/2926361-650bd2397a5b2.jpg",
   "href": "https://www.digitalsummit.com/philadelphia/speaker/2291637/dale-bertrand"
  },
  {
   "city": "philadelphia",
   "name": "Mindy Weinstein",
   "title": "CEO",
   "company": "Market MindShift",
   "image": "https://assets.swoogo.com/uploads/medium/5596013-68894890bf1a1.png",
   "href": "https://www.digitalsummit.com/philadelphia/speaker/2291638/mindy-weinstein"
  },
  {
   "city": "philadelphia",
   "name": "Kevin Snow",
   "title": "Founder",
   "company": "Time on Target",
   "image": "https://assets.swoogo.com/uploads/medium/2961876-6515bc106168a.jpg",
   "href": "https://www.digitalsummit.com/philadelphia/speaker/2291639/kevin-snow"
  },
  {
   "city": "philadelphia",
   "name": "Brent Bowen",
   "title": "Owner",
   "company": "Sparkcade Marketing",
   "image": "https://assets.swoogo.com/uploads/medium/3060666-652e87280fd06.jpg",
   "href": "https://www.digitalsummit.com/philadelphia/speaker/2291640/brent-bowen"
  },
  {
   "city": "philadelphia",
   "name": "Cynthia Round",
   "title": "Brand and Marketing Strategist",
   "company": "Independent Advisor",
   "image": "https://assets.swoogo.com/uploads/medium/4120786-667db9e29273a.png",
   "href": "https://www.digitalsummit.com/philadelphia/speaker/2291641/cynthia-round"
  },
  {
   "city": "philadelphia",
   "name": "Tyler Lane",
   "title": "CEO & Founder",
   "company": "Session Interactive",
   "image": "https://assets.swoogo.com/uploads/medium/5415071-683e5a1fa849c.png",
   "href": "https://www.digitalsummit.com/philadelphia/speaker/2291754/tyler-lane"
  },
  {
   "city": "philadelphia",
   "name": "Purna Virji",
   "title": "Founder",
   "company": "Agent-Led Growth",
   "image": "https://assets.swoogo.com/uploads/medium/2926342-650bcf271ec44.jpg",
   "href": "https://www.digitalsummit.com/philadelphia/speaker/2291869/purna-virji"
  },
  {
   "city": "philadelphia",
   "name": "Christina Clark",
   "title": "Head of Product , SEO",
   "company": "HubSpot",
   "image": "https://assets.swoogo.com/uploads/medium/2959766-6515a0eeee58e.jpg",
   "href": "https://www.digitalsummit.com/philadelphia/speaker/2291870/christina-clark"
  },
  {
   "city": "philadelphia",
   "name": "Ann Handley",
   "title": "Wall Street Journal Bestselling Author and Keynote Speaker",
   "company": "",
   "image": "https://assets.swoogo.com/uploads/medium/6894789-69e69ea6981e8.png",
   "href": "https://www.digitalsummit.com/philadelphia/speaker/2291876/ann-handley"
  },
  {
   "city": "philadelphia",
   "name": "Carmen Collins",
   "title": "Director of Social Media",
   "company": "Generac",
   "image": "https://assets.swoogo.com/uploads/medium/3721944-66044344258c6.png",
   "href": "https://www.digitalsummit.com/philadelphia/speaker/2291881/carmen-collins"
  },
  {
   "city": "philadelphia",
   "name": "Dawn Farrell",
   "title": "Digital Marketing Strategy Lead",
   "company": "SEI",
   "image": "https://assets.swoogo.com/uploads/medium/6894834-69e6a0d4aa04d.png",
   "href": "https://www.digitalsummit.com/philadelphia/speaker/2291882/dawn-farrell"
  },
  {
   "city": "philadelphia",
   "name": "Andy Crestodina",
   "title": "Co-Founder and CMO",
   "company": "Orbit Media Studios",
   "image": "https://assets.swoogo.com/uploads/medium/4823608-6792c23dc727d.png",
   "href": "https://www.digitalsummit.com/philadelphia/speaker/2313815/andy-crestodina"
  },
  {
   "city": "philadelphia",
   "name": "Kim Gallagher",
   "title": "Executive Director of Marketing & Customer Success",
   "company": "Nuuly",
   "image": "https://assets.swoogo.com/uploads/medium/7055555-6a10776871084.png",
   "href": "https://www.digitalsummit.com/philadelphia/speaker/2316815/kim-gallagher"
  },
  {
   "city": "philadelphia",
   "name": "Ralph Burns",
   "title": "Founder & CEO",
   "company": "Tier 11",
   "image": "https://assets.swoogo.com/uploads/medium/6995299-69fe3edc524da.png",
   "href": "https://www.digitalsummit.com/philadelphia/speaker/2317083/ralph-burns"
  },
  {
   "city": "philadelphia",
   "name": "Jen Kavanagh",
   "title": "Senior Vice President of Media and Marketing",
   "company": "Philadelphia Eagles",
   "image": "https://assets.swoogo.com/uploads/medium/7104839-6a2097e2b1000.png",
   "href": "https://www.digitalsummit.com/philadelphia/speaker/2354754/jen-kavanagh"
  },
  {
   "city": "philadelphia",
   "name": "Thalia K. Patrinos",
   "title": "Communication Strategist",
   "company": "NASA",
   "image": "https://assets.swoogo.com/uploads/medium/7195836-6a3e904fdd403.png",
   "href": "https://www.digitalsummit.com/philadelphia/speaker/2386241/thalia-k.-patrinos"
  },
  {
   "city": "philadelphia",
   "name": "Dolly Meckler",
   "title": "Founder",
   "company": "Scrollodex",
   "image": "https://assets.swoogo.com/uploads/medium/7245448-6a4fe1c07955f.png",
   "href": "https://www.digitalsummit.com/philadelphia/speaker/2405104/dolly-meckler"
  },
  {
   "city": "atlanta",
   "name": "Zuri Godfrey",
   "title": "Founder & Creator",
   "company": "",
   "image": "https://assets.swoogo.com/uploads/medium/3988162-6658a1b9e44bd.png",
   "href": "https://www.digitalsummit.com/atlanta/speaker/2315075/zuri-godfrey"
  },
  {
   "city": "atlanta",
   "name": "Nick Myers",
   "title": "Director of AI Innovation",
   "company": "Recovery.com",
   "image": "https://assets.swoogo.com/uploads/medium/6987106-69fcb4d5a7493.png",
   "href": "https://www.digitalsummit.com/atlanta/speaker/2315108/nick-myers"
  },
  {
   "city": "atlanta",
   "name": "Valerie Morrow",
   "title": "Director of Social Media",
   "company": "Dairy Farmers of America",
   "image": "https://assets.swoogo.com/uploads/medium/7022533-6a064cd536701.png",
   "href": "https://www.digitalsummit.com/atlanta/speaker/2326543/valerie-morrow"
  },
  {
   "city": "atlanta",
   "name": "Christina Garnett",
   "title": "Fractional CCO and Author",
   "company": "",
   "image": "https://assets.swoogo.com/uploads/medium/3756884-66101e52aeefb.png",
   "href": "https://www.digitalsummit.com/atlanta/speaker/2328278/christina-garnett"
  },
  {
   "city": "atlanta",
   "name": "Greg Swan",
   "title": "Senior Partner, Head of Futures & Client Transformation",
   "company": "FINN Partners",
   "image": "https://assets.swoogo.com/uploads/medium/7027665-6a0779362d5f0.png",
   "href": "https://www.digitalsummit.com/atlanta/speaker/2328346/greg-swan"
  },
  {
   "city": "atlanta",
   "name": "Carolyn Lyden",
   "title": "Director of SEO/AEO/GEO",
   "company": "EverPro",
   "image": "https://assets.swoogo.com/uploads/medium/7026688-6a076a2725780.png",
   "href": "https://www.digitalsummit.com/atlanta/speaker/2328379/carolyn-lyden"
  },
  {
   "city": "atlanta",
   "name": "Carson Mason",
   "title": "Sr. Community Associate",
   "company": "DraftKings Inc.",
   "image": "https://assets.swoogo.com/uploads/medium/4627726-673294fbce1fb.png",
   "href": "https://www.digitalsummit.com/atlanta/speaker/2328445/carson-mason"
  },
  {
   "city": "atlanta",
   "name": "Tyrona (Ty) Heath",
   "title": "Global Director, Thought Leadership GTM Strategy",
   "company": "LinkedIn",
   "image": "https://assets.swoogo.com/uploads/medium/2961612-6515b9c5b5246.jpg",
   "href": "https://www.digitalsummit.com/atlanta/speaker/2330213/tyrona-ty-heath"
  },
  {
   "city": "atlanta",
   "name": "Nick Westergaard",
   "title": "Author, Educator, and Speaker",
   "company": "",
   "image": "https://assets.swoogo.com/uploads/medium/4184077-66982cc180182.png",
   "href": "https://www.digitalsummit.com/atlanta/speaker/2335168/nick-westergaard"
  },
  {
   "city": "atlanta",
   "name": "John Triplett",
   "title": "Business Development Director",
   "company": "IDX",
   "image": "https://assets.swoogo.com/uploads/medium/6105647-691ce52ed104f.png",
   "href": "https://www.digitalsummit.com/atlanta/speaker/2335172/john-triplett"
  },
  {
   "city": "atlanta",
   "name": "Sharon Harris",
   "title": "CMO",
   "company": "The SH Collective",
   "image": "https://assets.swoogo.com/uploads/medium/4485349-66fc538c07a02.png",
   "href": "https://www.digitalsummit.com/atlanta/speaker/2335173/sharon-harris"
  },
  {
   "city": "atlanta",
   "name": "Dwayne Waite Jr",
   "title": "Associate Director of Marketing",
   "company": "Schell Games",
   "image": "https://assets.swoogo.com/uploads/medium/3978318-6655deadba1fc.png",
   "href": "https://www.digitalsummit.com/atlanta/speaker/2335178/dwayne-waite-jr"
  },
  {
   "city": "atlanta",
   "name": "Juntae DeLane",
   "title": "Marketing Director & Founder",
   "company": "DIGITAL DELANE",
   "image": "https://assets.swoogo.com/uploads/medium/2958364-65158c9c5edbb.jpg",
   "href": "https://www.digitalsummit.com/atlanta/speaker/2335180/juntae-delane"
  },
  {
   "city": "atlanta",
   "name": "Nicki Snyder",
   "title": "CMO",
   "company": "American Road Group",
   "image": "https://assets.swoogo.com/uploads/medium/3613408-65dd13b70c131.jpg",
   "href": "https://www.digitalsummit.com/atlanta/speaker/2335181/nicki-snyder"
  },
  {
   "city": "atlanta",
   "name": "Jerri Helms",
   "title": "SVP, Marketing Operations",
   "company": "HarperCollins Christian Publishing",
   "image": "https://assets.swoogo.com/uploads/medium/4664853-6745f3139bdd8.png",
   "href": "https://www.digitalsummit.com/atlanta/speaker/2335182/jerri-helms"
  },
  {
   "city": "atlanta",
   "name": "Tyria Saul",
   "title": "Founder/Principal",
   "company": "Omaris Digital",
   "image": "https://assets.swoogo.com/img/avatar.png",
   "href": "https://www.digitalsummit.com/atlanta/speaker/2335184/tyria-saul"
  },
  {
   "city": "atlanta",
   "name": "Beverly Jackson",
   "title": "Vice President, Brand, Product, and Integrated Marketing",
   "company": "Zillow",
   "image": "https://assets.swoogo.com/uploads/medium/7056181-6a109442df16d.png",
   "href": "https://www.digitalsummit.com/atlanta/speaker/2338121/beverly-jackson"
  },
  {
   "city": "atlanta",
   "name": "Jay Schwedelson",
   "title": "Founder",
   "company": "SubjectLine.com / GURU Media Hub",
   "image": "https://assets.swoogo.com/uploads/medium/4510008-67053e5023adf.png",
   "href": "https://www.digitalsummit.com/atlanta/speaker/2382566/jay-schwedelson"
  },
  {
   "city": "atlanta",
   "name": "Kate James",
   "title": "Senior Director, Global Resource Allocation",
   "company": "The Coca-Cola Company",
   "image": "https://assets.swoogo.com/uploads/medium/7243926-6a4fb204463b2.png",
   "href": "https://www.digitalsummit.com/atlanta/speaker/2404835/kate-james"
  }
 ],
 ":type": "sheet"
}